{
  "trigger": true,
  "modules": [
    "custom"
  ],
  "parentResource": "lmsauth",
  "functionName": "lmsauthPostAuthentication",
  "resourceName": "lmsauthPostAuthentication",
  "parentStack": "auth",
  "triggerEnvs": "[]",
  "triggerDir": "/snapshot/amplify-cli/build/node_modules/@aws-amplify/amplify-category-auth/provider-utils/awscloudformation/triggers/PostAuthentication",
  "triggerTemplate": "PostAuthentication.json.ejs",
  "triggerEventPath": "PostAuthentication.event.json",
  "roleName": "lmsauthPostAuthentication",
  "skipEdit": true,
  "enableCors": false
}